fly_elephant_mcp_server/__init__ .py
fly_elephant_mcp_server/__main__.py
fly_elephant_mcp_server/main.py
fly_elephant_mcp_server-0.1.14.dist-info/METADATA
fly_elephant_mcp_server-0.1.14.dist-info/WHEEL
fly_elephant_mcp_server-0.1.14.dist-info/entry_points.txt
fly_elephant_mcp_server-0.1.14.dist-info/top_level.txt
fly_elephant_mcp_server-0.1.14.dist-info/RECORD
