Metadata-Version: 2.4
Name: fly_elephant_mcp_server
Version: 0.1.14
Summary: Add your description here
Requires-Python: >=3.11
Requires-Dist: httpx>=0.28.1
Requires-Dist: mcp>=1.6.0
